MANIFEST.in
README.rst
setup.cfg
setup.py
docs/CHANGES.rst
docs/LICENSE.txt
src/pmr/__init__.py
src/pmr.wfctrl.egg-info/PKG-INFO
src/pmr.wfctrl.egg-info/SOURCES.txt
src/pmr.wfctrl.egg-info/dependency_links.txt
src/pmr.wfctrl.egg-info/entry_points.txt
src/pmr.wfctrl.egg-info/namespace_packages.txt
src/pmr.wfctrl.egg-info/not-zip-safe
src/pmr.wfctrl.egg-info/requires.txt
src/pmr.wfctrl.egg-info/top_level.txt
src/pmr/wfctrl/__init__.py
src/pmr/wfctrl/cmd.py
src/pmr/wfctrl/core.py
src/pmr/wfctrl/utils.py
src/pmr/wfctrl/testing/__init__.py
src/pmr/wfctrl/testing/base.py