Metadata-Version: 1.1
Name: pmr.wfctrl
Version: 0.1.0
Summary: Workflow controller
Home-page: http://github.com/PMR/pmr.wfctrl
Author: UNKNOWN
Author-email: UNKNOWN
License: gpl
Platform: UNKNOWN
Classifier: Programming Language :: Python
